zogyp/ZOGY.py
zogyp/__init__.py
zogyp/spali2.py
zogyp/zip.py
zogyp/zo_coadd.py
zogyp/configfls/check.param
zogyp/configfls/check.sex
zogyp/configfls/default.conv
zogyp/configfls/default.nnw
zogyp/configfls/default.param
zogyp/configfls/default.sex
zogyp/configfls/psfex.conf
zogyp/configfls/spali.param
zogyp/configfls/spali.sex
zogyp/test/1.fits
zogyp/test/2.fits
zogyp-1.6.3.dist-info/LICENSE.txt
zogyp-1.6.3.dist-info/METADATA
zogyp-1.6.3.dist-info/WHEEL
zogyp-1.6.3.dist-info/entry_points.txt
zogyp-1.6.3.dist-info/top_level.txt
zogyp-1.6.3.dist-info/RECORD
