Metadata-Version: 2.1
Name: zogyp
Version: 1.6.3
Summary: A parallel version of ZOGY image subtraction for astronomy, with Proper Co-Addition and Image alignment
Home-page: https://zogy-in-parallel.readthedocs.io/en/latest/
Author: Ry Cutter
Author-email: R.Cutter@warwick.ac.uk
License: General Public License v3.0
Platform: UNKNOWN
